MANIFEST.in
setup.py
django_jquery_autosuggest.egg-info/PKG-INFO
django_jquery_autosuggest.egg-info/SOURCES.txt
django_jquery_autosuggest.egg-info/dependency_links.txt
django_jquery_autosuggest.egg-info/requires.txt
django_jquery_autosuggest.egg-info/top_level.txt
jquery_autosuggest/__init__.py
jquery_autosuggest/models.py
jquery_autosuggest/static/css/autoSuggest.css
jquery_autosuggest/static/js/jquery.autoSuggest.js