Metadata-Version: 1.1
Name: django-jquery-autosuggest
Version: 1.4.1
Summary: jQuery autosuggest (http://code.drewwilson.com/entry/autosuggest-jquery-plugin) packaged in a django app to speed up new applications and deployment.
Home-page: https://github.com/benbacardi/django-jquery-autosuggest
Author: Ben Cardy
Author-email: benbacardi@gmail.com
License: MIT
Keywords: django,jquery,autosuggest,staticfiles
Platform: any
Classifier: Development Status :: 5 - Production/Stable
Classifier: Environment :: Web Environment
Classifier: Framework :: Django
Classifier: Intended Audience :: Developers
Classifier: Natural Language :: English
Classifier: License :: OSI Approved :: MIT License
Classifier: Operating System :: OS Independent
Classifier: Programming Language :: Python
Classifier: Topic :: Utilities
